setup.py
zfx_txt/__init__.py
zfx_txt/修改指定行内容.py
zfx_txt/删除指定行.py
zfx_txt/删除空行.py
zfx_txt/取关键词出现次数.py
zfx_txt/取指定行内容.py
zfx_txt/取指定行内容_分割.py
zfx_txt/取指定行内容_取中间.py
zfx_txt/取指定行内容_取出现次数.py
zfx_txt/取指定行内容_取右边.py
zfx_txt/取指定行内容_取左边.py
zfx_txt/取指定行内容_取长度.py
zfx_txt/取行数.py
zfx_txt/指定行插入内容.py
zfx_txt/替换指定内容.py
zfx_txt/统计字符数.py
zfx_txt/读入全部内容.py
zfx_txt/读运行目录文件.py
zfx_txt/追加内容.py
zfx_txt/重写内容.py
zfx_txt.egg-info/PKG-INFO
zfx_txt.egg-info/SOURCES.txt
zfx_txt.egg-info/dependency_links.txt
zfx_txt.egg-info/top_level.txt