Metadata-Version: 2.1
Name: zfx_txt
Version: 1.0.1
Summary: 这是一个用于 .txt 文件相关功能 Python 工具库,欢迎各路大神反馈意见及提出需求。企鹅号：424491679,企鹅群：961483644
Home-page: 
Author: zengfengxiang
Author-email: 424491679@qq.com
